{"name": "Law_enforcement_in_India", "id": 1234980, "predecessors": [{"name": "Government_of_India", "id": 1081194}, {"name": "Law_of_India", "id": 38350546}, {"name": "Emergency_services", "id": 1318794}, {"name": "Countries_in_Asia", "id": 37691781}], "successors": [{"name": "Indian_police_officers", "id": 4639637}, {"name": "Prisoners_and_detainees_of_India", "id": 17799810}, {"name": "Fugitives_wanted_by_India", "id": 16940022}, {"name": "Indian_crime_television_series", "id": 18583537}, {"name": "Indian_crime_films", "id": 31281018}, {"name": "Indian_politicians_convicted_of_crimes", "id": 31675973}, {"name": "Crime_in_Tamil_Nadu", "id": 40617629}, {"name": "Indian_gangsters", "id": 60961912}, {"name": "Judges_of_the_Allahabad_High_Court", "id": 31528235}, {"name": "Judges_of_the_Madras_High_Court", "id": 34587815}, {"name": "Chief_justices_of_the_Madras_High_Court", "id": 38484788}, {"name": "Fictional_portrayals_of_the_Tamil_Nadu_Police", "id": 52497278}, {"name": "Judges_of_the_Calcutta_High_Court", "id": 34587891}, {"name": "Inmates_of_Tihar_Jail", "id": 42108344}, {"name": "Indian_people_imprisoned_during_the_Emergency_(India)", "id": 42383470}, {"name": "20th-century_mass_murder_in_India", "id": 61215444}, {"name": "21st-century_mass_murder_in_India", "id": 61215446}]}