{"name": "English_domestic_cricket_competitions", "id": 2515106, "predecessors": [{"name": "Competitions", "id": 737119}, {"name": "Coastal_and_oceanic_landforms", "id": 11062641}, {"name": "Wikipedia_categorization", "id": 1036222}], "successors": [{"name": "Pro40", "id": 34984412}, {"name": "English_domestic_cricket_competition_stubs", "id": 75843411}, {"name": "County_Championship_seasons", "id": 50773145}, {"name": "Friends_Provident_Trophy_seasons", "id": 50387592}, {"name": "Birmingham_Phoenix_cricketers", "id": 68524204}, {"name": "London_Spirit_cricketers", "id": 68524181}]}