{"name": "European_bridge_(structure)_stubs", "id": 33589555, "predecessors": [{"name": "Bridge_(structure)_stubs", "id": 3455158}, {"name": "Europe_transport_stubs", "id": 33215288}, {"name": "European_building_and_structure_stubs", "id": 43129700}, {"name": "Wikipedia_maintenance", "id": 738040}], "successors": [{"name": "United_Kingdom_bridge_(structure)_stubs", "id": 6864065}, {"name": "Norwegian_bridge_(structure)_stubs", "id": 29032003}, {"name": "French_bridge_(structure)_stubs", "id": 34264348}, {"name": "Portuguese_bridge_(structure)_stubs", "id": 46262233}, {"name": "Swedish_bridge_(structure)_stubs", "id": 46272355}]}