{"name": "Ryukyuan_people", "id": 34052074, "predecessors": [{"name": "Ethnic_groups_in_Japan", "id": 3484488}, {"name": "Ryukyu_Islands", "id": 987440}, {"name": "Regions_of_Asia", "id": 4544939}, {"name": "Wikipedia_categorization", "id": 1036222}, {"name": "Plate_tectonics", "id": 717341}], "successors": [{"name": "Ueekata", "id": 23742129}, {"name": "17th-century_Ryukyuan_people", "id": 47403242}, {"name": "18th-century_Ryukyuan_people", "id": 47403290}, {"name": "19th-century_Ryukyuan_people", "id": 47403447}]}