{"name": "Poland_stubs", "id": 42976591, "predecessors": [{"name": "Europe_stubs", "id": 2964869}, {"name": "Countries_in_Europe", "id": 37691805}, {"name": "Wikipedia_categorization", "id": 1036222}, {"name": "Contents", "id": 14105005}], "successors": [{"name": "Poland_geography_stubs", "id": 1428490}, {"name": "Polish_people_stubs", "id": 1953825}, {"name": "Polish_history_stubs", "id": 3032946}, {"name": "Polish_military_stubs", "id": 5954507}, {"name": "Warsaw_stubs", "id": 7820703}, {"name": "Polish_company_stubs", "id": 15494959}, {"name": "Polish_sport_stubs", "id": 29132295}, {"name": "Polish_heraldry_stubs", "id": 30725776}, {"name": "Poland_politics_stubs", "id": 31024006}, {"name": "Poland_transport_stubs", "id": 33580490}, {"name": "Mass_media_in_Poland_stubs", "id": 37530789}, {"name": "Polish_building_and_structure_stubs", "id": 43153415}, {"name": "Poland_stub_templates", "id": 49369861}, {"name": "Polish_organisation_stubs", "id": 73469291}]}