{"name": "1962_by_country", "id": 4308749, "predecessors": [{"name": "20th_century", "id": 884457}, {"name": "Contemporary_history_by_country", "id": 36688060}], "successors": [{"name": "1962_in_the_Soviet_Union", "id": 11567590}, {"name": "1962_establishments_in_Australia", "id": 29626790}, {"name": "1962_establishments_in_England", "id": 30690518}, {"name": "1962_establishments_in_the_United_Kingdom", "id": 30690521}, {"name": "1962_establishments_in_Japan", "id": 33165331}, {"name": "1962_disestablishments_in_England", "id": 39265532}, {"name": "1962_disestablishments_in_Wales", "id": 49609169}, {"name": "1962_American_television_series_endings", "id": 38028991}]}