{"name": "Physical_cosmology", "id": 5114206, "predecessors": [{"name": "Astrophysics", "id": 698070}, {"name": "Theoretical_physics", "id": 691938}, {"name": "Academic_disciplines", "id": 693763}], "successors": [{"name": "General_relativity", "id": 782202}, {"name": "Large-scale_structure_of_the_cosmos", "id": 902074}, {"name": "Cosmologists", "id": 973775}, {"name": "Dark_matter", "id": 3349266}, {"name": "Cosmic_microwave_background_experiments", "id": 26375132}, {"name": "Cosmology_books", "id": 36217605}, {"name": "Physics_beyond_the_Standard_Model", "id": 37781448}, {"name": "Physical_cosmology_stubs", "id": 71314548}, {"name": "Isaac_Newton", "id": 1505776}, {"name": "Creation_myths", "id": 15715670}]}