{"name": "1990_films", "id": 742875, "predecessors": [{"name": "1990s_in_film", "id": 10148236}, {"name": "20th_century", "id": 884457}, {"name": "Historiography", "id": 895940}], "successors": [{"name": "1990_television_films", "id": 18174096}, {"name": "1990_horror_films", "id": 36662774}, {"name": "1990_comedy_films", "id": 61539854}, {"name": "1990_directorial_debut_films", "id": 63550091}, {"name": "1990_drama_films", "id": 63653660}, {"name": "1990_independent_films", "id": 63793073}, {"name": "1990_documentary_films", "id": 63800678}, {"name": "1990_action_films", "id": 64444973}, {"name": "1990_anime_OVAs", "id": 37651910}]}