{"name": "WikiProject_Arthropods_articles", "id": 7441968, "predecessors": [{"name": "Wikipedia_collaborations", "id": 1572809}], "successors": [{"name": "GA-Class_Arthropods_articles", "id": 7912190}, {"name": "B-Class_Arthropods_articles", "id": 7912200}, {"name": "Start-Class_Arthropods_articles", "id": 7912216}, {"name": "Stub-Class_Arthropods_articles", "id": 7912227}, {"name": "List-Class_Arthropods_articles", "id": 11139677}, {"name": "C-Class_Arthropods_articles", "id": 18227405}, {"name": "Category-Class_Arthropods_pages", "id": 55536126}, {"name": "Disambig-Class_Arthropods_pages", "id": 55536130}, {"name": "Template-Class_Arthropods_pages", "id": 55536139}, {"name": "Redirect-Class_Arthropods_pages", "id": 61891989}, {"name": "High-importance_Arthropods_articles", "id": 7918115}, {"name": "Mid-importance_Arthropods_articles", "id": 7918140}, {"name": "Low-importance_Arthropods_articles", "id": 7918161}, {"name": "NA-importance_Arthropods_pages", "id": 21238431}]}