{"name": "Languages_of_India", "id": 934333, "predecessors": [{"name": "Indian_culture", "id": 33349475}, {"name": "Wikipedia_categorization", "id": 1036222}, {"name": "Geography", "id": 693800}], "successors": [{"name": "Dravidian_languages", "id": 768616}, {"name": "Hindi", "id": 1123882}, {"name": "Urdu", "id": 1370400}, {"name": "Tamil_language", "id": 1740828}, {"name": "Malayalam_language", "id": 3005945}, {"name": "Linguistic_history_of_India", "id": 4043802}, {"name": "Indian_words_and_phrases", "id": 24369216}, {"name": "Endangered_languages_of_India", "id": 36820359}, {"name": "Urdu-language_writers_from_India", "id": 17207406}, {"name": "English-language_writers_from_India", "id": 26133413}, {"name": "Kannada_literature", "id": 1766481}, {"name": "Sanskrit_texts", "id": 2660445}, {"name": "Tamil-language_literature", "id": 2835304}, {"name": "Urdu-language_literature", "id": 3006119}, {"name": "Bengali-language_literature", "id": 3382366}, {"name": "Hindi-language_literature", "id": 4223119}, {"name": "Marathi-language_literature", "id": 4716760}, {"name": "Telugu-language_literature", "id": 6012597}, {"name": "Assamese_literature", "id": 10068564}, {"name": "Malayalam-language_literature", "id": 10570611}, {"name": "Sanskrit_literature", "id": 11101520}, {"name": "Meitei_literature", "id": 71001021}, {"name": "Punjabi-language_writers", "id": 17340276}, {"name": "Recipients_of_the_Sahitya_Akademi_Award_in_Punjabi", "id": 39555568}, {"name": "Odia-language_writers", "id": 35550170}, {"name": "Recipients_of_the_Sahitya_Akademi_Award_in_Odia", "id": 39574986}, {"name": "Recipients_of_the_Odisha_Sahitya_Akademi_Award", "id": 70897358}, {"name": "Sanskrit_poetry", "id": 27560448}, {"name": "Punjabi-language_poets", "id": 5564152}, {"name": "Urdu-language_poets_from_India", "id": 18535526}, {"name": "English-language_poets_from_India", "id": 26133395}, {"name": "Languages_of_Assam", "id": 34576049}, {"name": "Languages_of_Nagaland", "id": 50513816}, {"name": "Dhivehi-language_films", "id": 72424170}, {"name": "Sanskrit_words_and_phrases", "id": 9951197}, {"name": "Sanskrit_writers", "id": 29401587}, {"name": "Telugu-language_writers", "id": 35974628}, {"name": "Urdu-language_Indian_films", "id": 72266743}]}